{
  "sections": {
    "main": {
      "type": "main-page",
      "disabled": true,
      "settings": {
        "show_title": false,
        "page_width": "medium"
      }
    },
    "preheat_banner_form_E8wUNm": {
      "type": "preheat-banner-form",
      "settings": {
        "background_image": "shopify:\/\/shop_images\/i1.jpg",
        "background_image_mobile": "shopify:\/\/shop_images\/i2.jpg",
        "text": "Enter now for the chance to become our Honourary Tester.",
        "text1": "Enter your email below for a chance to be among lucky Testers to try the new Air5 for free!",
        "text2": "Enter email",
        "text3": "subscribe"
      }
    },
    "preheat_sticky_bottom_CNcq6L": {
      "type": "preheat-sticky-bottom",
      "settings": {
        "text": "Ulike Air 10",
        "text1": "Worth £369",
        "text2": "Enter for a chance to become our Honourary Tester.",
        "text3": "Enter now"
      }
    },
    "preheat_roster_mndTwt": {
      "type": "preheat-roster",
      "settings": {
        "text": "Daily Winner Announcement",
        "text1": "The patented Sapphire Ice technology, paired with the provided gel, minimizes discomfort, even in sensitive and delicate areas.",
        "text2": "<ul><li>Set*** @gmail.com<\/li><li>Set*** @gmail.com<\/li><li>Set*** @gmail.com<\/li><li>Set*** @gmail.com<\/li><li>Set*** @gmail.com<\/li><li>Set*** @gmail.com<\/li><li>Set*** @gmail.com<\/li><li>Set*** @gmail.com<\/li><li>Set*** @gmail.com<\/li><li>Set*** @gmail.com<\/li><li>Set*** @gmail.com<\/li><li>Set*** @gmail.com<\/li><li>Set*** @gmail.com<\/li><li>Set*** @gmail.com<\/li><li>Set*** @gmail.com<\/li><li>Set*** @gmail.com<\/li><li>Set*** @gmail.com<\/li><li>Set*** @gmail.com<\/li><li>Set*** @gmail.com<\/li><\/ul>"
      }
    }
  },
  "order": [
    "main",
    "preheat_banner_form_E8wUNm",
    "preheat_sticky_bottom_CNcq6L",
    "preheat_roster_mndTwt"
  ]
}